{
  "authorDailyContributionsMap": {
    "erjillsison": [
      {
        "insertions": 0,
        "deletions": 0,
        "date": "2019-02-10",
        "commitResults": []
      },
      {
        "insertions": 0,
        "deletions": 0,
        "date": "2019-02-11",
        "commitResults": []
      },
      {
        "insertions": 0,
        "deletions": 0,
        "date": "2019-02-12",
        "commitResults": []
      },
      {
        "insertions": 0,
        "deletions": 0,
        "date": "2019-02-13",
        "commitResults": []
      },
      {
        "insertions": 0,
        "deletions": 0,
        "date": "2019-02-14",
        "commitResults": []
      },
      {
        "insertions": 0,
        "deletions": 1,
        "date": "2019-02-15",
        "commitResults": [
          {
            "hash": "86e5eb1621f76450e2e9b8ac47a6ab3eb9f399a4",
            "message": "Remove codacy badge from README",
            "insertions": 0,
            "deletions": 1
          }
        ]
      },
      {
        "insertions": 0,
        "deletions": 0,
        "date": "2019-02-16",
        "commitResults": []
      },
      {
        "insertions": 4,
        "deletions": 0,
        "date": "2019-02-17",
        "commitResults": [
          {
            "hash": "5c1c6ae49554ab2249d962bf7c66d4c4bfffa1e8",
            "message": "Add AddCommand alias",
            "insertions": 2,
            "deletions": 0
          },
          {
            "hash": "c8ea52699ed4c71fa313156e0ac1775d279fdd3c",
            "message": "Add DeleteCommand alias",
            "insertions": 2,
            "deletions": 0
          }
        ]
      },
      {
        "insertions": 15,
        "deletions": 0,
        "date": "2019-02-18",
        "commitResults": [
          {
            "hash": "63a081776b37ed18cf24e56b2680a113f45acb87",
            "message": "Add test for COMMAND_ALIAS",
            "insertions": 15,
            "deletions": 0
          }
        ]
      },
      {
        "insertions": 20,
        "deletions": 37,
        "date": "2019-02-19",
        "commitResults": [
          {
            "hash": "2973214c540abbbd50bf49d2013a2cc40787a0fe",
            "message": "Update UserGuide.adoc",
            "insertions": 9,
            "deletions": 26
          },
          {
            "hash": "9625184f383434e3e07a350540de2500914ccf28",
            "message": "Update README.adoc to display UI mockup",
            "insertions": 2,
            "deletions": 2
          },
          {
            "hash": "f84586b15b38163a961a4340226ee983d5c65fd5",
            "message": "Update README.adoc",
            "insertions": 4,
            "deletions": 4
          },
          {
            "hash": "c69d5466c448c9c90a5c56bfbe8d7b1e37e1ff5f",
            "message": "Change Erjill photo to png",
            "insertions": 3,
            "deletions": 3
          },
          {
            "hash": "43cce412c812ee997dd2875eac088f7bb08686d2",
            "message": "Rename UG and DG titles",
            "insertions": 2,
            "deletions": 2
          }
        ]
      },
      {
        "insertions": 0,
        "deletions": 0,
        "date": "2019-02-20",
        "commitResults": []
      },
      {
        "insertions": 2,
        "deletions": 2,
        "date": "2019-02-21",
        "commitResults": [
          {
            "hash": "4ab8f985a5f454c8b24ad8b329e10722dbe8c01c",
            "message": "Update build.gradle site-name and site-githuburl",
            "insertions": 2,
            "deletions": 2
          }
        ]
      },
      {
        "insertions": 0,
        "deletions": 0,
        "date": "2019-02-22",
        "commitResults": []
      },
      {
        "insertions": 0,
        "deletions": 0,
        "date": "2019-02-23",
        "commitResults": []
      },
      {
        "insertions": 0,
        "deletions": 0,
        "date": "2019-02-24",
        "commitResults": []
      },
      {
        "insertions": 0,
        "deletions": 0,
        "date": "2019-02-25",
        "commitResults": []
      },
      {
        "insertions": 79,
        "deletions": 11,
        "date": "2019-02-26",
        "commitResults": [
          {
            "hash": "73452516333180955ca8948521b49292becb2319",
            "message": "Create InitialiseMapCommandParser.java",
            "insertions": 42,
            "deletions": 0
          },
          {
            "hash": "c86c41d7d17d80dd661e1867b83c308980a1a59a",
            "message": "Update ParserUtil to include parseMapSize",
            "insertions": 14,
            "deletions": 0
          },
          {
            "hash": "302a948dbb63155332209e7d7b095d15a63cf8d4",
            "message": "Update AddressBookParser.java to return InitialiseMapCommand",
            "insertions": 16,
            "deletions": 2
          },
          {
            "hash": "093335e541deec392844e75775cb99be8573149a",
            "message": "Update InitialiseMapCommand.java",
            "insertions": 5,
            "deletions": 8
          },
          {
            "hash": "583cdf7b34fcefc6dcc73d051ee7d25ef75afbc9",
            "message": "Update ParserUtil.java with MESSAGE_INVALID_SIZE",
            "insertions": 2,
            "deletions": 1
          }
        ]
      },
      {
        "insertions": 1145,
        "deletions": 1089,
        "date": "2019-02-27",
        "commitResults": [
          {
            "hash": "36e53a3bb5796d59dc0886809effd0a8694e6769",
            "message": "Create constructor for Person.java that requires no arguments",
            "insertions": 13,
            "deletions": 1
          },
          {
            "hash": "ff368f66da4268bb6e4095cf553ddce290679c58",
            "message": "Remove checks if person added is unique",
            "insertions": 7,
            "deletions": 1
          },
          {
            "hash": "5b001940abcc72280799775e79fbb3a167f4b48e",
            "message": "Update InitialiseMapCommand to clear address book and set to a fixed size",
            "insertions": 7,
            "deletions": 3
          },
          {
            "hash": "366f98e4f1209c48202a78c35f270c120b1abf81",
            "message": "Create InitialiseMapCommand.java",
            "insertions": 60,
            "deletions": 0
          },
          {
            "hash": "c1c144bd42beedb8619e755bbed53cc56a0f7da5",
            "message": "Teach app to take in \u0027init command but return AddCommand",
            "insertions": 5,
            "deletions": 14
          },
          {
            "hash": "e430a0694becf709323d78609914652b6931115d",
            "message": "Remove tests that check for duplicate persons",
            "insertions": 5,
            "deletions": 23
          },
          {
            "hash": "224e098c0d10d68a2378249af5283f146baaf1b0",
            "message": "Revert \"Merge pull request #16 from lucydotc/master\"",
            "insertions": 37,
            "deletions": 37
          },
          {
            "hash": "dd8e09f2271b1b9491a6f4fe8c9e6dcaac625f39",
            "message": "Refactor AddressBook to MapGrid",
            "insertions": 234,
            "deletions": 233
          },
          {
            "hash": "a0e8f30e11555ef8e6eda408a8d3c8d3a7ab973e",
            "message": "Refactor Person to Cell",
            "insertions": 777,
            "deletions": 777
          }
        ]
      },
      {
        "insertions": 354,
        "deletions": 214,
        "date": "2019-02-28",
        "commitResults": [
          {
            "hash": "b59d7d92620c5b7ae4f4fb947f993b66407db35d",
            "message": "Add getMapSize() method in Model",
            "insertions": 28,
            "deletions": 0
          },
          {
            "hash": "3538cba83c2e954083853e8205616a4ddcdc840e",
            "message": "Add Battlship attribute in Cell",
            "insertions": 16,
            "deletions": 1
          },
          {
            "hash": "941ef712311a9e7daae6fe7df125f2b418491f63",
            "message": "Add Battlship attribute in Cell",
            "insertions": 16,
            "deletions": 1
          },
          {
            "hash": "7f235b92e8ecea01c61b3e0c3c2bb990081ee78c",
            "message": "Add hasBattleShip method in Cell",
            "insertions": 10,
            "deletions": 0
          },
          {
            "hash": "52e272f4578995ab5880b6eb8dade3450fd6e134",
            "message": "Refactor person package to cell",
            "insertions": 123,
            "deletions": 122
          },
          {
            "hash": "e7ec3d118e5d5442a72f6946161d708fc619d0de",
            "message": "Refactor rename UniquePersonList to Row",
            "insertions": 146,
            "deletions": 58
          },
          {
            "hash": "80725721f26b1f6a50ea144c201ea9cee5ac75b9",
            "message": "Update comments in Row.java",
            "insertions": 2,
            "deletions": 30
          },
          {
            "hash": "ad6e344af75a98f36a894bac8eaccba6fe266686",
            "message": "Create Status enum",
            "insertions": 8,
            "deletions": 0
          },
          {
            "hash": "f86c3976dc3a8847cc5f376aa89a23a3a8c5346d",
            "message": "Add Status attribute to Cell",
            "insertions": 4,
            "deletions": 1
          },
          {
            "hash": "8f188b1076cede2c70341bb3f5bdfa05b0131022",
            "message": "Update Cell default name as \"This cell is empty\" placeholder",
            "insertions": 1,
            "deletions": 1
          }
        ]
      },
      {
        "insertions": 80,
        "deletions": 29,
        "date": "2019-03-01",
        "commitResults": [
          {
            "hash": "aad7eb1f484f3ceb113b570b366b005b519dedad",
            "message": "Update UserGuide.adoc",
            "insertions": 4,
            "deletions": 10
          },
          {
            "hash": "a1c216640d65359209555a9ef63c748af4c27fef",
            "message": "Add new user stories and use cases in the DG",
            "insertions": 8,
            "deletions": 14
          },
          {
            "hash": "9869f997cdff130962676ed477f03dfab992327b",
            "message": "Update InitialiseMapCommand to have max and min size",
            "insertions": 9,
            "deletions": 5
          },
          {
            "hash": "634d986af4454ba2dfd01239dddb6845e5b2817e",
            "message": "Create InitialiseMapCommandTest.java",
            "insertions": 59,
            "deletions": 0
          }
        ]
      },
      {
        "insertions": 1,
        "deletions": 1,
        "date": "2019-03-02",
        "commitResults": [
          {
            "hash": "0e6fa31546c15721d669f8f82e35026cdfc25fc7",
            "message": "Fix formatting of UG",
            "insertions": 1,
            "deletions": 1
          }
        ]
      },
      {
        "insertions": 0,
        "deletions": 0,
        "date": "2019-03-03",
        "commitResults": []
      },
      {
        "insertions": 45,
        "deletions": 2,
        "date": "2019-03-04",
        "commitResults": [
          {
            "hash": "76a77dd0cbce74918b1b3f5bd211cb861ab30122",
            "message": "Add putShip method in Model component",
            "insertions": 45,
            "deletions": 2
          }
        ]
      },
      {
        "insertions": 10,
        "deletions": 10,
        "date": "2019-03-05",
        "commitResults": [
          {
            "hash": "d3f13a4f87c1539dd55ea80beb0a105c97a75451",
            "message": "Update responsibilities in AboutUs.adoc",
            "insertions": 10,
            "deletions": 10
          }
        ]
      },
      {
        "insertions": 117,
        "deletions": 12,
        "date": "2019-03-06",
        "commitResults": [
          {
            "hash": "ea1a08647119189e561c145056d2e7de1450747d",
            "message": "Add getMapGrid to Model interface",
            "insertions": 16,
            "deletions": 0
          },
          {
            "hash": "0ce012e408badb7d122f1f52361747bc4351c36d",
            "message": "Add getCell in MapGrid.java",
            "insertions": 7,
            "deletions": 0
          },
          {
            "hash": "2e0bf624098bbfcc2241b1dc8f18b73011bce95c",
            "message": "Add an updateUi method in Model",
            "insertions": 63,
            "deletions": 2
          },
          {
            "hash": "c1ce6906f0d44f4c2981c67db9cdb97ecde149a0",
            "message": "Add initialise and getCell in MapGrid",
            "insertions": 18,
            "deletions": 9
          },
          {
            "hash": "afd47468c83f4db34325545e263781cb41fd35d4",
            "message": "Add getMapGrid() to Logic",
            "insertions": 9,
            "deletions": 0
          },
          {
            "hash": "03e10a8cd11a8428f2ba1c437b0d8c11c1723c68",
            "message": "Add 2D array to hold Cell in MapGrid",
            "insertions": 4,
            "deletions": 1
          }
        ]
      },
      {
        "insertions": 67,
        "deletions": 2253,
        "date": "2019-03-07",
        "commitResults": [
          {
            "hash": "9c7afacca8ab3d09e0fcc632557acf248ca07a44",
            "message": "Update UI to display 2D Grid",
            "insertions": 27,
            "deletions": 30
          },
          {
            "hash": "024ffc9b0ceb04f42e59613ecd0687ad0d0f1632",
            "message": "Cell in UI will change colour according to Status",
            "insertions": 25,
            "deletions": 1
          },
          {
            "hash": "c524a1ad7a261f445e1b89a8ec09ca41f7e8d594",
            "message": "Update putShip in Cell to change status to SHIP",
            "insertions": 1,
            "deletions": 0
          },
          {
            "hash": "20b0cdd3b66e7d4949e50545df9c18de2a35de0d",
            "message": "Delete CellListPanelTest.java",
            "insertions": 0,
            "deletions": 104
          },
          {
            "hash": "e6e9139104ace3dc65098a259b87a6242e572a0d",
            "message": "Delete AddCommandTest.java",
            "insertions": 0,
            "deletions": 288
          },
          {
            "hash": "a33353c7e46ce8c825767fa4fae0bd32ffd06aed",
            "message": "Update getCell in MapGrid",
            "insertions": 1,
            "deletions": 1
          },
          {
            "hash": "da808959bb3d518b6eb0cdcf15dd2431651cdfc2",
            "message": "Delete SystemTests that are irrelevant to Battleship",
            "insertions": 0,
            "deletions": 1804
          },
          {
            "hash": "2cacd67705fef68226715816ece612f3e8d3ffea",
            "message": "Remove systemtests from TestApp",
            "insertions": 0,
            "deletions": 10
          },
          {
            "hash": "c6864588f14563f0cc8032e13427ef15db30b1d8",
            "message": "Fix checkstyle issues",
            "insertions": 12,
            "deletions": 14
          },
          {
            "hash": "3f73a8009a58b8ed58216f7de78d6a2f328d5b1b",
            "message": "Update InitialiseMapCommandTest.java",
            "insertions": 1,
            "deletions": 1
          }
        ]
      },
      {
        "insertions": 0,
        "deletions": 0,
        "date": "2019-03-08",
        "commitResults": []
      },
      {
        "insertions": 0,
        "deletions": 0,
        "date": "2019-03-09",
        "commitResults": []
      },
      {
        "insertions": 24,
        "deletions": 0,
        "date": "2019-03-10",
        "commitResults": [
          {
            "hash": "3eb46bf76c51f4fd0d4a03f10f1e12333f48f138",
            "message": "Add a receiveAttack() in Cell",
            "insertions": 24,
            "deletions": 0
          }
        ]
      },
      {
        "insertions": 44,
        "deletions": 20,
        "date": "2019-03-11",
        "commitResults": [
          {
            "hash": "a26d3524d978120e8828c180c7125088adeb4d55",
            "message": "Remove prefix for mapsize in IntialiseMapCommand",
            "insertions": 10,
            "deletions": 20
          },
          {
            "hash": "6d730b75bb95eadd8a05fea6778d0e71404661bc",
            "message": "Create InitialiseMapCommandParserTest.java",
            "insertions": 34,
            "deletions": 0
          }
        ]
      },
      {
        "insertions": 0,
        "deletions": 0,
        "date": "2019-03-12",
        "commitResults": []
      },
      {
        "insertions": 48,
        "deletions": 16,
        "date": "2019-03-13",
        "commitResults": [
          {
            "hash": "bc2ce2d7b4c44d8cd51f3a2b180b334a430f2034",
            "message": "Refactor logic of initialise map from MapGrid to InitialiseMapCommand",
            "insertions": 13,
            "deletions": 7
          },
          {
            "hash": "fe1d0c950d903cb9313ed4e7800af77dba4c1cd7",
            "message": "Remove unnecessary print statement",
            "insertions": 0,
            "deletions": 1
          },
          {
            "hash": "5ff0146a6796351a5f7bb4a541606bed0e7cb832",
            "message": "Create utility class that returns an empty size ten map",
            "insertions": 27,
            "deletions": 0
          },
          {
            "hash": "79e833608d250d2dfec7bbc204b866367285fda0",
            "message": "Ignore PutShipCommandTest",
            "insertions": 8,
            "deletions": 8
          }
        ]
      },
      {
        "insertions": 0,
        "deletions": 0,
        "date": "2019-03-14",
        "commitResults": []
      },
      {
        "insertions": 171,
        "deletions": 44,
        "date": "2019-03-15",
        "commitResults": [
          {
            "hash": "609fb1a2621b208768195b580d296f074a6cf489",
            "message": "Rework Cell Status and how they are displayed in the UI",
            "insertions": 29,
            "deletions": 15
          },
          {
            "hash": "05dfbb000d92dee7dd6d1699a59928ac8f84a3a9",
            "message": "Update CellTest.java",
            "insertions": 21,
            "deletions": 0
          },
          {
            "hash": "4174b13e6c1a00889e2e8f146bc36d3d7ec4578a",
            "message": "Update DeveloperGuide.adoc with Map Feature implementation",
            "insertions": 24,
            "deletions": 0
          },
          {
            "hash": "90d6e81aa383dd5ad7127fbdf764a9f8792f32d6",
            "message": "Add putShip and attackCell in MapGrid",
            "insertions": 27,
            "deletions": 14
          },
          {
            "hash": "31d6236cb951289dc053867a39943725cd57fc94",
            "message": "Remove putShip() from ModelManager",
            "insertions": 0,
            "deletions": 12
          },
          {
            "hash": "979f6c0c0f625d2ca4d0608173cbddd66fd6991b",
            "message": "Add get2dArrayMapGridCopy() in MapGrid",
            "insertions": 33,
            "deletions": 1
          },
          {
            "hash": "da83e8c5fbc6773acf6772e694d7ee36fb1bfe4d",
            "message": "Remove unused import statements",
            "insertions": 0,
            "deletions": 2
          },
          {
            "hash": "6d480f7180e1ee95587b9ffc6b2aa8efb5203b64",
            "message": "Update CellTest and MapGridTest",
            "insertions": 37,
            "deletions": 0
          }
        ]
      },
      {
        "insertions": 158,
        "deletions": 137,
        "date": "2019-03-16",
        "commitResults": [
          {
            "hash": "930e872a160d21d7361bdf509adebbfb85c98a3f",
            "message": "Add row and columns labels to MapGrid",
            "insertions": 113,
            "deletions": 108
          },
          {
            "hash": "0187b87ff3b7eb116bcf7c0a3106803fc73b4142",
            "message": "Add mininum width to map panel and \"Your board\" text",
            "insertions": 6,
            "deletions": 4
          },
          {
            "hash": "fd77e6ef8445ac88aa4ba8184f783c58434fb8c2",
            "message": "Fix map grid placing",
            "insertions": 2,
            "deletions": 2
          },
          {
            "hash": "74c445a44aaf6b2debc07baad31a3a17bfe788c0",
            "message": "Fix Cell copy constructor",
            "insertions": 1,
            "deletions": 0
          },
          {
            "hash": "a31481e7c59db8783c904995bb3c9bf7053b1b22",
            "message": "Refactor hasBattleShip in Cell",
            "insertions": 1,
            "deletions": 4
          },
          {
            "hash": "d79609d303fb3b95608bdac4a123af0074b4ffa1",
            "message": "Refactor MapGrid",
            "insertions": 13,
            "deletions": 6
          },
          {
            "hash": "6518d0312791e7a294b80c10cab88b9bead64866",
            "message": "Add Coordinates attribute to Cell for equality checking",
            "insertions": 19,
            "deletions": 1
          },
          {
            "hash": "c362f426dbb36e818de369f3635f92db3ecfa0eb",
            "message": "Update SizeTenMapGrid.java",
            "insertions": 3,
            "deletions": 1
          },
          {
            "hash": "c030719c3c8b0a91e1ec4c008261514eb078ae8c",
            "message": "Remove Cell constructor that requires battleship",
            "insertions": 0,
            "deletions": 11
          }
        ]
      },
      {
        "insertions": 158,
        "deletions": 93,
        "date": "2019-03-17",
        "commitResults": [
          {
            "hash": "3fd14b70c798b1e7679f9dd44eacadfd1b8fe2c8",
            "message": "Update equals method of Cell to check for coordinates and battleship",
            "insertions": 5,
            "deletions": 1
          },
          {
            "hash": "ba398967590c73f6059ec3b58519be024398902d",
            "message": "Update toString() of Cell to display coordinates",
            "insertions": 1,
            "deletions": 9
          },
          {
            "hash": "1ebd9ede2f500ee8312145c0d5f731ed8045d5f3",
            "message": "Change methods in PlayerMap to private",
            "insertions": 4,
            "deletions": 4
          },
          {
            "hash": "f3c1482a84020c6b5fa166e6fdf7a4a904ca1ad8",
            "message": "Show both maps in the UI",
            "insertions": 148,
            "deletions": 78
          },
          {
            "hash": "0f5e5e79782667829ffb26be14562522ec23c8c2",
            "message": "Remove unused imports",
            "insertions": 0,
            "deletions": 1
          }
        ]
      },
      {
        "insertions": 0,
        "deletions": 0,
        "date": "2019-03-18",
        "commitResults": []
      }
    ],
    "iwle": [
      {
        "insertions": 0,
        "deletions": 0,
        "date": "2019-02-10",
        "commitResults": []
      },
      {
        "insertions": 0,
        "deletions": 0,
        "date": "2019-02-11",
        "commitResults": []
      },
      {
        "insertions": 0,
        "deletions": 0,
        "date": "2019-02-12",
        "commitResults": []
      },
      {
        "insertions": 0,
        "deletions": 0,
        "date": "2019-02-13",
        "commitResults": []
      },
      {
        "insertions": 0,
        "deletions": 0,
        "date": "2019-02-14",
        "commitResults": []
      },
      {
        "insertions": 0,
        "deletions": 0,
        "date": "2019-02-15",
        "commitResults": []
      },
      {
        "insertions": 0,
        "deletions": 0,
        "date": "2019-02-16",
        "commitResults": []
      },
      {
        "insertions": 0,
        "deletions": 0,
        "date": "2019-02-17",
        "commitResults": []
      },
      {
        "insertions": 0,
        "deletions": 0,
        "date": "2019-02-18",
        "commitResults": []
      },
      {
        "insertions": 0,
        "deletions": 0,
        "date": "2019-02-19",
        "commitResults": []
      },
      {
        "insertions": 0,
        "deletions": 0,
        "date": "2019-02-20",
        "commitResults": []
      },
      {
        "insertions": 0,
        "deletions": 0,
        "date": "2019-02-21",
        "commitResults": []
      },
      {
        "insertions": 0,
        "deletions": 0,
        "date": "2019-02-22",
        "commitResults": []
      },
      {
        "insertions": 0,
        "deletions": 0,
        "date": "2019-02-23",
        "commitResults": []
      },
      {
        "insertions": 0,
        "deletions": 0,
        "date": "2019-02-24",
        "commitResults": []
      },
      {
        "insertions": 0,
        "deletions": 0,
        "date": "2019-02-25",
        "commitResults": []
      },
      {
        "insertions": 0,
        "deletions": 0,
        "date": "2019-02-26",
        "commitResults": []
      },
      {
        "insertions": 0,
        "deletions": 0,
        "date": "2019-02-27",
        "commitResults": []
      },
      {
        "insertions": 0,
        "deletions": 0,
        "date": "2019-02-28",
        "commitResults": []
      },
      {
        "insertions": 0,
        "deletions": 0,
        "date": "2019-03-01",
        "commitResults": []
      },
      {
        "insertions": 0,
        "deletions": 0,
        "date": "2019-03-02",
        "commitResults": []
      },
      {
        "insertions": 0,
        "deletions": 0,
        "date": "2019-03-03",
        "commitResults": []
      },
      {
        "insertions": 0,
        "deletions": 0,
        "date": "2019-03-04",
        "commitResults": []
      },
      {
        "insertions": 0,
        "deletions": 0,
        "date": "2019-03-05",
        "commitResults": []
      },
      {
        "insertions": 0,
        "deletions": 0,
        "date": "2019-03-06",
        "commitResults": []
      },
      {
        "insertions": 0,
        "deletions": 0,
        "date": "2019-03-07",
        "commitResults": []
      },
      {
        "insertions": 0,
        "deletions": 0,
        "date": "2019-03-08",
        "commitResults": []
      },
      {
        "insertions": 0,
        "deletions": 0,
        "date": "2019-03-09",
        "commitResults": []
      },
      {
        "insertions": 0,
        "deletions": 0,
        "date": "2019-03-10",
        "commitResults": []
      },
      {
        "insertions": 0,
        "deletions": 0,
        "date": "2019-03-11",
        "commitResults": []
      },
      {
        "insertions": 0,
        "deletions": 0,
        "date": "2019-03-12",
        "commitResults": []
      },
      {
        "insertions": 0,
        "deletions": 0,
        "date": "2019-03-13",
        "commitResults": []
      },
      {
        "insertions": 0,
        "deletions": 0,
        "date": "2019-03-14",
        "commitResults": []
      },
      {
        "insertions": 0,
        "deletions": 0,
        "date": "2019-03-15",
        "commitResults": []
      },
      {
        "insertions": 0,
        "deletions": 0,
        "date": "2019-03-16",
        "commitResults": []
      },
      {
        "insertions": 0,
        "deletions": 0,
        "date": "2019-03-17",
        "commitResults": []
      },
      {
        "insertions": 0,
        "deletions": 0,
        "date": "2019-03-18",
        "commitResults": []
      }
    ],
    "lucydotc": [
      {
        "insertions": 0,
        "deletions": 0,
        "date": "2019-02-10",
        "commitResults": []
      },
      {
        "insertions": 0,
        "deletions": 0,
        "date": "2019-02-11",
        "commitResults": []
      },
      {
        "insertions": 0,
        "deletions": 0,
        "date": "2019-02-12",
        "commitResults": []
      },
      {
        "insertions": 0,
        "deletions": 0,
        "date": "2019-02-13",
        "commitResults": []
      },
      {
        "insertions": 0,
        "deletions": 0,
        "date": "2019-02-14",
        "commitResults": []
      },
      {
        "insertions": 0,
        "deletions": 0,
        "date": "2019-02-15",
        "commitResults": []
      },
      {
        "insertions": 0,
        "deletions": 0,
        "date": "2019-02-16",
        "commitResults": []
      },
      {
        "insertions": 0,
        "deletions": 0,
        "date": "2019-02-17",
        "commitResults": []
      },
      {
        "insertions": 0,
        "deletions": 0,
        "date": "2019-02-18",
        "commitResults": []
      },
      {
        "insertions": 0,
        "deletions": 0,
        "date": "2019-02-19",
        "commitResults": []
      },
      {
        "insertions": 0,
        "deletions": 0,
        "date": "2019-02-20",
        "commitResults": []
      },
      {
        "insertions": 0,
        "deletions": 0,
        "date": "2019-02-21",
        "commitResults": []
      },
      {
        "insertions": 0,
        "deletions": 0,
        "date": "2019-02-22",
        "commitResults": []
      },
      {
        "insertions": 0,
        "deletions": 0,
        "date": "2019-02-23",
        "commitResults": []
      },
      {
        "insertions": 0,
        "deletions": 0,
        "date": "2019-02-24",
        "commitResults": []
      },
      {
        "insertions": 0,
        "deletions": 0,
        "date": "2019-02-25",
        "commitResults": []
      },
      {
        "insertions": 0,
        "deletions": 0,
        "date": "2019-02-26",
        "commitResults": []
      },
      {
        "insertions": 0,
        "deletions": 0,
        "date": "2019-02-27",
        "commitResults": []
      },
      {
        "insertions": 0,
        "deletions": 0,
        "date": "2019-02-28",
        "commitResults": []
      },
      {
        "insertions": 0,
        "deletions": 0,
        "date": "2019-03-01",
        "commitResults": []
      },
      {
        "insertions": 0,
        "deletions": 0,
        "date": "2019-03-02",
        "commitResults": []
      },
      {
        "insertions": 0,
        "deletions": 0,
        "date": "2019-03-03",
        "commitResults": []
      },
      {
        "insertions": 0,
        "deletions": 0,
        "date": "2019-03-04",
        "commitResults": []
      },
      {
        "insertions": 188,
        "deletions": 17,
        "date": "2019-03-05",
        "commitResults": [
          {
            "hash": "9fe78f471b7a70c9b317f68836c623088a30cb6b",
            "message": "Add enemy turn Use Cases to Developer Guide",
            "insertions": 31,
            "deletions": 8
          },
          {
            "hash": "0999d5aef3e40063a7dd213ec7c49d655ebbf5d2",
            "message": "Add enemyturn to User Guide",
            "insertions": 15,
            "deletions": 1
          },
          {
            "hash": "a82bd64a9d4078087ec4f5c50abd5ca1e2f79170",
            "message": "Update Fleet constructor",
            "insertions": 15,
            "deletions": 4
          },
          {
            "hash": "5fc346d222ff469da2d3380e71360970bab7321a",
            "message": "Update Player constructor Add support for valid name check",
            "insertions": 28,
            "deletions": 4
          },
          {
            "hash": "415bc9e67a6945dc164d8e14b1fc4fa977aab6e1",
            "message": "Add Fleet Test Fix checkstyle issues",
            "insertions": 40,
            "deletions": 0
          },
          {
            "hash": "00bd3cdf5968961d1d43ded8f25f5b6d280a20de",
            "message": "Add Player Test Fix checkstyle errors",
            "insertions": 59,
            "deletions": 0
          }
        ]
      },
      {
        "insertions": 0,
        "deletions": 0,
        "date": "2019-03-06",
        "commitResults": []
      },
      {
        "insertions": 0,
        "deletions": 0,
        "date": "2019-03-07",
        "commitResults": []
      },
      {
        "insertions": 0,
        "deletions": 0,
        "date": "2019-03-08",
        "commitResults": []
      },
      {
        "insertions": 0,
        "deletions": 0,
        "date": "2019-03-09",
        "commitResults": []
      },
      {
        "insertions": 0,
        "deletions": 0,
        "date": "2019-03-10",
        "commitResults": []
      },
      {
        "insertions": 0,
        "deletions": 0,
        "date": "2019-03-11",
        "commitResults": []
      },
      {
        "insertions": 0,
        "deletions": 0,
        "date": "2019-03-12",
        "commitResults": []
      },
      {
        "insertions": 0,
        "deletions": 0,
        "date": "2019-03-13",
        "commitResults": []
      },
      {
        "insertions": 90,
        "deletions": 5,
        "date": "2019-03-14",
        "commitResults": [
          {
            "hash": "3352c9b570e5b131d48144c7d6ed5b8b3e73fc06",
            "message": "Add enemy player",
            "insertions": 62,
            "deletions": 0
          },
          {
            "hash": "037333168442c0cacdd0f4fb2cd40b7e003cdbf5",
            "message": "Update Player class with targetHistory set",
            "insertions": 23,
            "deletions": 4
          },
          {
            "hash": "5b54397bedf31dbb4e04eb799fb95b8da5bf0f49",
            "message": "Update Player test with test_targetHistory",
            "insertions": 5,
            "deletions": 1
          }
        ]
      },
      {
        "insertions": 0,
        "deletions": 0,
        "date": "2019-03-15",
        "commitResults": []
      },
      {
        "insertions": 0,
        "deletions": 0,
        "date": "2019-03-16",
        "commitResults": []
      },
      {
        "insertions": 0,
        "deletions": 0,
        "date": "2019-03-17",
        "commitResults": []
      },
      {
        "insertions": 0,
        "deletions": 0,
        "date": "2019-03-18",
        "commitResults": []
      }
    ],
    "bos10": [
      {
        "insertions": 0,
        "deletions": 0,
        "date": "2019-02-10",
        "commitResults": []
      },
      {
        "insertions": 0,
        "deletions": 0,
        "date": "2019-02-11",
        "commitResults": []
      },
      {
        "insertions": 0,
        "deletions": 0,
        "date": "2019-02-12",
        "commitResults": []
      },
      {
        "insertions": 0,
        "deletions": 0,
        "date": "2019-02-13",
        "commitResults": []
      },
      {
        "insertions": 0,
        "deletions": 0,
        "date": "2019-02-14",
        "commitResults": []
      },
      {
        "insertions": 0,
        "deletions": 0,
        "date": "2019-02-15",
        "commitResults": []
      },
      {
        "insertions": 0,
        "deletions": 0,
        "date": "2019-02-16",
        "commitResults": []
      },
      {
        "insertions": 0,
        "deletions": 0,
        "date": "2019-02-17",
        "commitResults": []
      },
      {
        "insertions": 0,
        "deletions": 0,
        "date": "2019-02-18",
        "commitResults": []
      },
      {
        "insertions": 0,
        "deletions": 0,
        "date": "2019-02-19",
        "commitResults": []
      },
      {
        "insertions": 0,
        "deletions": 0,
        "date": "2019-02-20",
        "commitResults": []
      },
      {
        "insertions": 0,
        "deletions": 0,
        "date": "2019-02-21",
        "commitResults": []
      },
      {
        "insertions": 0,
        "deletions": 0,
        "date": "2019-02-22",
        "commitResults": []
      },
      {
        "insertions": 0,
        "deletions": 0,
        "date": "2019-02-23",
        "commitResults": []
      },
      {
        "insertions": 0,
        "deletions": 0,
        "date": "2019-02-24",
        "commitResults": []
      },
      {
        "insertions": 0,
        "deletions": 0,
        "date": "2019-02-25",
        "commitResults": []
      },
      {
        "insertions": 0,
        "deletions": 0,
        "date": "2019-02-26",
        "commitResults": []
      },
      {
        "insertions": 0,
        "deletions": 0,
        "date": "2019-02-27",
        "commitResults": []
      },
      {
        "insertions": 25,
        "deletions": 21,
        "date": "2019-02-28",
        "commitResults": [
          {
            "hash": "5de890b7709b8ee1064a0c7e93cd057246f4886e",
            "message": "Refactor HistoryCommand to StatsCommand",
            "insertions": 25,
            "deletions": 21
          }
        ]
      },
      {
        "insertions": 33,
        "deletions": 21,
        "date": "2019-03-01",
        "commitResults": [
          {
            "hash": "9575242ee90ec8031a915b5aa2159309a630e8c9",
            "message": "Updated StatsCommand to track only successful commands",
            "insertions": 5,
            "deletions": 5
          },
          {
            "hash": "8088fdb06168c3cd86a4006f939ae15b90f986af",
            "message": "Allow StatsCommand to display frequency of valid commands",
            "insertions": 15,
            "deletions": 2
          },
          {
            "hash": "74bd2d840a7481f985271116e6d3c936501d8757",
            "message": "Display frequency for keyword command only",
            "insertions": 9,
            "deletions": 9
          },
          {
            "hash": "08b779c0e5e0481defa064d721744fab87c43ad6",
            "message": "Updated UserGuide for \u0027stats\u0027 command",
            "insertions": 4,
            "deletions": 5
          }
        ]
      },
      {
        "insertions": 0,
        "deletions": 0,
        "date": "2019-03-02",
        "commitResults": []
      },
      {
        "insertions": 11,
        "deletions": 8,
        "date": "2019-03-03",
        "commitResults": [
          {
            "hash": "091226d593d2bde914ed645a052b816f2c605b0f",
            "message": "Modified testing",
            "insertions": 11,
            "deletions": 8
          }
        ]
      },
      {
        "insertions": 0,
        "deletions": 0,
        "date": "2019-03-04",
        "commitResults": []
      },
      {
        "insertions": 18,
        "deletions": 5,
        "date": "2019-03-05",
        "commitResults": [
          {
            "hash": "fcc6c951caf56b61140de126f532c2428aa5c8cc",
            "message": "Updated Developer Guide for stats command and added getElapsedTime() method for CommandHistory in preparation to display elapsed time on statistics",
            "insertions": 15,
            "deletions": 1
          },
          {
            "hash": "d4807a9f5b31bbb7add42d1a40bd704601ddd6b4",
            "message": "fixed checkstyle error",
            "insertions": 3,
            "deletions": 4
          }
        ]
      },
      {
        "insertions": 0,
        "deletions": 0,
        "date": "2019-03-06",
        "commitResults": []
      },
      {
        "insertions": 0,
        "deletions": 0,
        "date": "2019-03-07",
        "commitResults": []
      },
      {
        "insertions": 0,
        "deletions": 0,
        "date": "2019-03-08",
        "commitResults": []
      },
      {
        "insertions": 0,
        "deletions": 0,
        "date": "2019-03-09",
        "commitResults": []
      },
      {
        "insertions": 0,
        "deletions": 0,
        "date": "2019-03-10",
        "commitResults": []
      },
      {
        "insertions": 0,
        "deletions": 0,
        "date": "2019-03-11",
        "commitResults": []
      },
      {
        "insertions": 57,
        "deletions": 53,
        "date": "2019-03-12",
        "commitResults": [
          {
            "hash": "4f80a26b07ffbca521f0cbaf530be7645492bad8",
            "message": "Added real-time game duration in GUI and removed relevant tests",
            "insertions": 53,
            "deletions": 43
          },
          {
            "hash": "eb97c982b6630002ae961faf3ba888a99d1bed92",
            "message": "fixed checkstyle errors",
            "insertions": 4,
            "deletions": 10
          }
        ]
      },
      {
        "insertions": 0,
        "deletions": 0,
        "date": "2019-03-13",
        "commitResults": []
      },
      {
        "insertions": 0,
        "deletions": 0,
        "date": "2019-03-14",
        "commitResults": []
      },
      {
        "insertions": 0,
        "deletions": 0,
        "date": "2019-03-15",
        "commitResults": []
      },
      {
        "insertions": 0,
        "deletions": 0,
        "date": "2019-03-16",
        "commitResults": []
      },
      {
        "insertions": 0,
        "deletions": 0,
        "date": "2019-03-17",
        "commitResults": []
      },
      {
        "insertions": 286,
        "deletions": 56,
        "date": "2019-03-18",
        "commitResults": [
          {
            "hash": "e3f6ae3bcd402d50278909ac291c0c5b73ac86c8",
            "message": "Added new Statistics Class",
            "insertions": 54,
            "deletions": 0
          },
          {
            "hash": "0014a77777131594a3e48b85b770af3c5fcb7a7c",
            "message": "Added javadocs comments",
            "insertions": 15,
            "deletions": 3
          },
          {
            "hash": "32e4c175a30029b58b8bd2a9e38057b9d8b1d915",
            "message": "fixed checkstyle errors",
            "insertions": 11,
            "deletions": 11
          },
          {
            "hash": "a97a20604ccdb55ed29c27e44b064a566dcb194d",
            "message": "fixed checkstyle errors",
            "insertions": 2,
            "deletions": 2
          },
          {
            "hash": "1e997111e4b540b2773dce87085cc2666abc7cf8",
            "message": "Added increment functions",
            "insertions": 15,
            "deletions": 0
          },
          {
            "hash": "85840724abc4d1661634865e7e240e5b45648333",
            "message": "Added increment functions",
            "insertions": 15,
            "deletions": 0
          },
          {
            "hash": "593f9b5fba3c5ccd19b9385bf73406c3096206b5",
            "message": "Updated javadocs",
            "insertions": 14,
            "deletions": 2
          },
          {
            "hash": "4956812339cd9a4c2c7b8296d187b10be66a1147",
            "message": "Updated javadocs",
            "insertions": 14,
            "deletions": 2
          },
          {
            "hash": "bceeb23c9fd820f70c7af2b05b15963071da1503",
            "message": "added getters methods",
            "insertions": 2,
            "deletions": 4
          },
          {
            "hash": "e1564ddaed256510ec3c2838ffaa5d3a94e26f22",
            "message": "added getters methods",
            "insertions": 2,
            "deletions": 4
          },
          {
            "hash": "1fb6ade88b9c45a915deb352941a1cef405d92c2",
            "message": "setup junit testing for statistics class methods",
            "insertions": 58,
            "deletions": 0
          },
          {
            "hash": "605388fbdf2679f80acbe93c1691fc52b2d7b0a3",
            "message": "setup junit testing for statistics class methods",
            "insertions": 58,
            "deletions": 0
          },
          {
            "hash": "2739c1ba0300756c3897ac620eac945d211f46e9",
            "message": "fixed addition problem in test and API",
            "insertions": 5,
            "deletions": 3
          },
          {
            "hash": "9f26f75f5c77f0b4254c87056d8186ad9a15f055",
            "message": "fixed addition problem in test and API",
            "insertions": 5,
            "deletions": 3
          },
          {
            "hash": "a013795615a6d661548ebbd91ffbc4927e643044",
            "message": "added the testing files and rectified checkstyle",
            "insertions": 0,
            "deletions": 2
          },
          {
            "hash": "dc2d0362f513f9dc64461739fa8a53f52919bf1b",
            "message": "added the testing files and rectified checkstyle",
            "insertions": 0,
            "deletions": 2
          },
          {
            "hash": "389f0cca409d9d260e3dfbb914b6246c8dc7a038",
            "message": "refactored accuracy method",
            "insertions": 1,
            "deletions": 1
          },
          {
            "hash": "a9425b42ab6e684a2537cb3f4a174a183e434972",
            "message": "refactored accuracy method",
            "insertions": 1,
            "deletions": 1
          },
          {
            "hash": "3a15beca0427462c8e34e539ceac419d6e0e897c",
            "message": "fixed testing for elapsedtime",
            "insertions": 14,
            "deletions": 16
          }
        ]
      }
    ],
    "s-tr": [
      {
        "insertions": 0,
        "deletions": 0,
        "date": "2019-02-10",
        "commitResults": []
      },
      {
        "insertions": 0,
        "deletions": 0,
        "date": "2019-02-11",
        "commitResults": []
      },
      {
        "insertions": 0,
        "deletions": 0,
        "date": "2019-02-12",
        "commitResults": []
      },
      {
        "insertions": 0,
        "deletions": 0,
        "date": "2019-02-13",
        "commitResults": []
      },
      {
        "insertions": 0,
        "deletions": 0,
        "date": "2019-02-14",
        "commitResults": []
      },
      {
        "insertions": 0,
        "deletions": 0,
        "date": "2019-02-15",
        "commitResults": []
      },
      {
        "insertions": 0,
        "deletions": 0,
        "date": "2019-02-16",
        "commitResults": []
      },
      {
        "insertions": 0,
        "deletions": 0,
        "date": "2019-02-17",
        "commitResults": []
      },
      {
        "insertions": 0,
        "deletions": 0,
        "date": "2019-02-18",
        "commitResults": []
      },
      {
        "insertions": 95,
        "deletions": 18,
        "date": "2019-02-19",
        "commitResults": [
          {
            "hash": "4e52bea317616441f3f6fb4afe83c199145f460c",
            "message": "Updated README.adoc",
            "insertions": 10,
            "deletions": 12
          },
          {
            "hash": "7cf5ae946a2cdfe0225163687777022bb25830fe",
            "message": "Further updated README.adoc.",
            "insertions": 4,
            "deletions": 3
          },
          {
            "hash": "c88b17e5666c253d4bf65529af20fd90fb677ef1",
            "message": "Change Travis build status image to reflect this repository\u0027s status instead of se-edu/addressbook-level4.",
            "insertions": 1,
            "deletions": 1
          },
          {
            "hash": "f1cce38f185edf3f14ce4dce58681c2badb41a7a",
            "message": "Add AddressBookStorage#backupAddressBook.",
            "insertions": 18,
            "deletions": 0
          },
          {
            "hash": "f9e2a9609721b74064f9f0ee07672b8431591189",
            "message": "Added logic for backupAddressBook.",
            "insertions": 17,
            "deletions": 1
          },
          {
            "hash": "ecbc430ec4b0516afa451cea82d5d0f3746e46f1",
            "message": "Added tests for backup().",
            "insertions": 44,
            "deletions": 0
          },
          {
            "hash": "a04cf5cb34d37571f94805fdd83108e7e12f998b",
            "message": "Fixed spacing.",
            "insertions": 1,
            "deletions": 1
          }
        ]
      },
      {
        "insertions": 0,
        "deletions": 0,
        "date": "2019-02-20",
        "commitResults": []
      },
      {
        "insertions": 0,
        "deletions": 0,
        "date": "2019-02-21",
        "commitResults": []
      },
      {
        "insertions": 0,
        "deletions": 0,
        "date": "2019-02-22",
        "commitResults": []
      },
      {
        "insertions": 0,
        "deletions": 0,
        "date": "2019-02-23",
        "commitResults": []
      },
      {
        "insertions": 0,
        "deletions": 0,
        "date": "2019-02-24",
        "commitResults": []
      },
      {
        "insertions": 0,
        "deletions": 0,
        "date": "2019-02-25",
        "commitResults": []
      },
      {
        "insertions": 0,
        "deletions": 0,
        "date": "2019-02-26",
        "commitResults": []
      },
      {
        "insertions": 0,
        "deletions": 0,
        "date": "2019-02-27",
        "commitResults": []
      },
      {
        "insertions": 0,
        "deletions": 0,
        "date": "2019-02-28",
        "commitResults": []
      },
      {
        "insertions": 0,
        "deletions": 0,
        "date": "2019-03-01",
        "commitResults": []
      },
      {
        "insertions": 36,
        "deletions": 0,
        "date": "2019-03-02",
        "commitResults": [
          {
            "hash": "673ac40e8617ec94a4f2c9530b4f419cea8aa40e",
            "message": "Add stub attack command file",
            "insertions": 21,
            "deletions": 0
          },
          {
            "hash": "bb65891fc114385be8ab154dc4d18dab31fbcf20",
            "message": "Add alias for Attack command",
            "insertions": 4,
            "deletions": 0
          },
          {
            "hash": "7953b2778f5a368713ba6b9ee9a2c335566d997e",
            "message": "Add stub Attack command parser",
            "insertions": 11,
            "deletions": 0
          }
        ]
      },
      {
        "insertions": 32,
        "deletions": 0,
        "date": "2019-03-03",
        "commitResults": [
          {
            "hash": "eb91b420335b2ecc5733590a8bccc2a206c6544b",
            "message": "Add stub Attack command parser test",
            "insertions": 32,
            "deletions": 0
          }
        ]
      },
      {
        "insertions": 145,
        "deletions": 76,
        "date": "2019-03-04",
        "commitResults": [
          {
            "hash": "60e94e86f3f843d0015c5fecf7df20b9267bc484",
            "message": "Add simple behaviour to AttackCommand",
            "insertions": 17,
            "deletions": 1
          },
          {
            "hash": "6d50579a7f3184896ae123dae343004a08840e3b",
            "message": "Convert spaces to tabs",
            "insertions": 38,
            "deletions": 27
          },
          {
            "hash": "6ff5adfb8c70862ab427f048b064560602be0bac",
            "message": "Add parse behaviour for AttackCommand in AddressBookParser",
            "insertions": 7,
            "deletions": 0
          },
          {
            "hash": "6487c08960d3b5f8027d514ac117057a3c320762",
            "message": "Add test for AttackCommandParser",
            "insertions": 25,
            "deletions": 6
          },
          {
            "hash": "bc858f36df2b79fc4355ec5dac4769d5af40ba6a",
            "message": "Add equals method for AttackCommand",
            "insertions": 11,
            "deletions": 1
          },
          {
            "hash": "fb1a2e0cebeea1c7feebea819eff58f12d12dd70",
            "message": "Minor style edits",
            "insertions": 0,
            "deletions": 3
          },
          {
            "hash": "bec4b4c3082f266f1afc11ab4df137dabc67fb36",
            "message": "Modify tabs to spaces in AttackCommandParserTest",
            "insertions": 28,
            "deletions": 28
          },
          {
            "hash": "ece090df4727dc30ca809562f864ece9aca4a06d",
            "message": "Fix style violations in AttackCommandParserTest",
            "insertions": 12,
            "deletions": 6
          },
          {
            "hash": "b7121fdf0601ec2ed379dafdbe2f36c1a7395c93",
            "message": "Fix unused import in AttackCommandParserTest",
            "insertions": 0,
            "deletions": 1
          },
          {
            "hash": "954d50fc50e4d36a77602a7f10b1e79ad0fc6955",
            "message": "Fix indentation in Fleet",
            "insertions": 5,
            "deletions": 2
          },
          {
            "hash": "14d353c213753d44308d00195c33236dc22e9f2a",
            "message": "Add generic type in Fleet to prevent unchecked assignment",
            "insertions": 2,
            "deletions": 1
          }
        ]
      },
      {
        "insertions": 0,
        "deletions": 0,
        "date": "2019-03-05",
        "commitResults": []
      },
      {
        "insertions": 0,
        "deletions": 0,
        "date": "2019-03-06",
        "commitResults": []
      },
      {
        "insertions": 0,
        "deletions": 0,
        "date": "2019-03-07",
        "commitResults": []
      },
      {
        "insertions": 0,
        "deletions": 0,
        "date": "2019-03-08",
        "commitResults": []
      },
      {
        "insertions": 51,
        "deletions": 0,
        "date": "2019-03-09",
        "commitResults": [
          {
            "hash": "abdf338a1e75cecbe65d0069e31ff2e841fec16b",
            "message": "Add base AttackResult class",
            "insertions": 51,
            "deletions": 0
          }
        ]
      },
      {
        "insertions": 80,
        "deletions": 41,
        "date": "2019-03-10",
        "commitResults": [
          {
            "hash": "e95cf0971544aa94206eec9abe08c43ddf6dc531",
            "message": "Add AttackMissed class",
            "insertions": 24,
            "deletions": 0
          },
          {
            "hash": "c1b31d6aa9ab3d13b098ca3ea7b676ebd16fabd5",
            "message": "Change AttackResult class to take Player object",
            "insertions": 9,
            "deletions": 7
          },
          {
            "hash": "c2623198424eaa4002fcabb869ab6c384e48973b",
            "message": "Add behaviour for Cell receiving an attack",
            "insertions": 31,
            "deletions": 9
          },
          {
            "hash": "0478011adac142390b71521ba45828fb5737aed4",
            "message": "Rework the way Status works",
            "insertions": 16,
            "deletions": 13
          },
          {
            "hash": "ea39b93a41995192f6161726a58a846fcf7cfcac",
            "message": "Modify behaviour of Cell.receiveAttack()",
            "insertions": 0,
            "deletions": 12
          }
        ]
      },
      {
        "insertions": 144,
        "deletions": 11,
        "date": "2019-03-11",
        "commitResults": [
          {
            "hash": "0f8015dee20d05b1e1c89cba0f559c4e820459ea",
            "message": "Remove unused import in CommandResult",
            "insertions": 0,
            "deletions": 1
          },
          {
            "hash": "7f79ebba9a32cd22b02f5b3acf4e056f3eee2446",
            "message": "Add stub Battle API class",
            "insertions": 63,
            "deletions": 0
          },
          {
            "hash": "6827b553165094c2f99c746a06c8d6c566993df0",
            "message": "Add constructor for BattleManager",
            "insertions": 14,
            "deletions": 8
          },
          {
            "hash": "c1f37f3fcdedbd0ef1ba5890e265c119ba2d1c21",
            "message": "Add more behaviour to BattleManager",
            "insertions": 4,
            "deletions": 2
          },
          {
            "hash": "1bb67873f32bfdc179bfd9bd0594cf183c8023a5",
            "message": "Add isHit() method to AttackResult",
            "insertions": 11,
            "deletions": 0
          },
          {
            "hash": "febbb9bafbb2f3f4c2aa1e7fb87309600841ff7b",
            "message": "Add new kinds of AttackResults",
            "insertions": 52,
            "deletions": 0
          }
        ]
      },
      {
        "insertions": 121,
        "deletions": 26,
        "date": "2019-03-12",
        "commitResults": [
          {
            "hash": "077ac02bacba5ee6aebadae872374f9d24a0ae95",
            "message": "Implemented performAttack() in BattleManager class",
            "insertions": 89,
            "deletions": 8
          },
          {
            "hash": "b061b2a2b12fbb8a9f386e5441a977e3cf3929ec",
            "message": "Improved the attacking process",
            "insertions": 7,
            "deletions": 3
          },
          {
            "hash": "0f6f86dbf7c39496ce826c0c2d1f3d55cd1fe8db",
            "message": "Improved the attacking process",
            "insertions": 22,
            "deletions": 13
          },
          {
            "hash": "e28faf4e8751d707b4bd4650fe95227e808a7d86",
            "message": "Changed AttackCommandParser to trim spaces from input",
            "insertions": 3,
            "deletions": 2
          }
        ]
      },
      {
        "insertions": 0,
        "deletions": 0,
        "date": "2019-03-13",
        "commitResults": []
      },
      {
        "insertions": 0,
        "deletions": 0,
        "date": "2019-03-14",
        "commitResults": []
      },
      {
        "insertions": 0,
        "deletions": 0,
        "date": "2019-03-15",
        "commitResults": []
      },
      {
        "insertions": 0,
        "deletions": 0,
        "date": "2019-03-16",
        "commitResults": []
      },
      {
        "insertions": 63,
        "deletions": 30,
        "date": "2019-03-17",
        "commitResults": [
          {
            "hash": "9549ddbcf87056382ee84abe53580e5a9eee5bb9",
            "message": "Updated BattleManager to use format string from AttackResult in logging",
            "insertions": 10,
            "deletions": 3
          },
          {
            "hash": "8c5685d0d0c9b25cfdaf6e9a00066343b94f1da8",
            "message": "Made changes to UserGuide to partially replace reference to AB4 with references to Battleships",
            "insertions": 25,
            "deletions": 24
          },
          {
            "hash": "bbb1a4af7b5666ae5ebb3c7e67f4ca77c08ff089",
            "message": "Change MainWindow to stop Timer in StatusBarFooter when app is closed",
            "insertions": 25,
            "deletions": 2
          },
          {
            "hash": "c1bd21ab7de73a7e4023e0d91ffff52b69e37730",
            "message": "Add check for statusBarFooter !\u003d null in handleExit()",
            "insertions": 3,
            "deletions": 1
          }
        ]
      },
      {
        "insertions": 29,
        "deletions": 40,
        "date": "2019-03-18",
        "commitResults": [
          {
            "hash": "a8e38673c86fd80cb4cc1170e41bc31945cdfaf7",
            "message": "Make changes to User Guide",
            "insertions": 16,
            "deletions": 13
          },
          {
            "hash": "16d28b9ff80eda40c993f48e539f0282c0f474b3",
            "message": "Remove unneeded command",
            "insertions": 0,
            "deletions": 5
          },
          {
            "hash": "0093b2ee6d42873d2dfb9eaaf8348c9dc77f5822",
            "message": "Remove more unneeded commands",
            "insertions": 1,
            "deletions": 8
          },
          {
            "hash": "f3c1e6e05e4454a3bda88b4146471d542aa97552",
            "message": "Modify the Quick Start section",
            "insertions": 3,
            "deletions": 4
          },
          {
            "hash": "d7e9a078a0d21139fd61749cdcd919c49efac4c6",
            "message": "Correct spelling and grammar",
            "insertions": 9,
            "deletions": 10
          }
        ]
      }
    ]
  },
  "authorFinalContributionMap": {
    "erjillsison": 1807,
    "iwle": 0,
    "lucydotc": 238,
    "bos10": 263,
    "s-tr": 621
  },
  "authorFileFormatContributionMap": {
    "erjillsison": {
      "adoc": 54,
      "cs": 0,
      "css": 0,
      "fxml": 10,
      "gradle": 2,
      "html": 0,
      "java": 1741,
      "js": 0,
      "json": 0,
      "jsp": 0,
      "md": 0,
      "py": 0,
      "tag": 0,
      "txt": 0,
      "xml": 0
    },
    "iwle": {
      "adoc": 0,
      "cs": 0,
      "css": 0,
      "fxml": 0,
      "gradle": 0,
      "html": 0,
      "java": 0,
      "js": 0,
      "json": 0,
      "jsp": 0,
      "md": 0,
      "py": 0,
      "tag": 0,
      "txt": 0,
      "xml": 0
    },
    "lucydotc": {
      "adoc": 38,
      "cs": 0,
      "css": 0,
      "fxml": 0,
      "gradle": 0,
      "html": 0,
      "java": 200,
      "js": 0,
      "json": 0,
      "jsp": 0,
      "md": 0,
      "py": 0,
      "tag": 0,
      "txt": 0,
      "xml": 0
    },
    "bos10": {
      "adoc": 2,
      "cs": 0,
      "css": 0,
      "fxml": 0,
      "gradle": 0,
      "html": 0,
      "java": 261,
      "js": 0,
      "json": 0,
      "jsp": 0,
      "md": 0,
      "py": 0,
      "tag": 0,
      "txt": 0,
      "xml": 0
    },
    "s-tr": {
      "adoc": 51,
      "cs": 0,
      "css": 0,
      "fxml": 0,
      "gradle": 0,
      "html": 0,
      "java": 570,
      "js": 0,
      "json": 0,
      "jsp": 0,
      "md": 0,
      "py": 0,
      "tag": 0,
      "txt": 0,
      "xml": 0
    }
  },
  "authorContributionVariance": {
    "erjillsison": 264785.9,
    "iwle": 0.0,
    "lucydotc": 1313.9885,
    "bos10": 3390.5376,
    "s-tr": 3002.592
  },
  "authorDisplayNameMap": {
    "erjillsison": "SIS...NES",
    "iwle": "IAN... EN",
    "lucydotc": "LUC...YAN",
    "bos10": "CHE...TON",
    "s-tr": "CHO...WEI"
  }
}
